libembroidery/__init__.py
libembroidery-1.0a0.dist-info/LICENCE
libembroidery-1.0a0.dist-info/METADATA
libembroidery-1.0a0.dist-info/WHEEL
libembroidery-1.0a0.dist-info/top_level.txt
libembroidery-1.0a0.dist-info/RECORD
